picamerax/__init__.py
picamerax/array.py
picamerax/bcm_host.py
picamerax/camera.py
picamerax/color.py
picamerax/display.py
picamerax/encoders.py
picamerax/exc.py
picamerax/frames.py
picamerax/mmal.py
picamerax/mmalobj.py
picamerax/renderers.py
picamerax/streams.py
picamerax/user_vcsm.py
picamerax/vcsmobj.py
picamerax-24.3.21.dist-info/LICENSE.txt
picamerax-24.3.21.dist-info/METADATA
picamerax-24.3.21.dist-info/WHEEL
picamerax-24.3.21.dist-info/top_level.txt
picamerax-24.3.21.dist-info/RECORD
